{
    "id": "thart-agus-thart",
    "title": "Thart agus Thart",
    "titleEnglish": "Around and Around",
    "album": "Single",
    "year": "2024",
    "duration": "3:18",
    "primaryLanguage": "bilingual",
    "lines": [
      {
        "type": "section",
        "section": "Hook"
      },
      {
        "english": "Thart agus thart",
        "irish": "Thart agus thart"
      },
      {
        "english": "Big skins, thíos ag an mini mart",
        "irish": "Páipéir mhóra rollta, down at the mini mart"
      },
      {
        "english": "Few loose Capri Sun and a Mars Bar",
        "irish": "Cúpla Capri Sun scaoilte agus barra Mars"
      },
      {
        "english": "Dúid mhór salach ansin tá mé thar barr",
        "irish": "Big dirty joint and now I'm grand"
      },
      {
        "english": "Thart agus thart",
        "irish": "Round and round"
      },
      {
        "english": "Cosúil le mo mhéilteoir ya",
        "irish": "Like my grinder, yeah"
      },
      {
        "english": "Fear beag gnaitheach when I'm on tour",
        "irish": "Busy little man when I'm on tour"
      },
      {
        "english": "No top, moshpit, sweaty balls, encore",
        "irish": "Gan léine, i lár an moshpit, liathróidí luiscthe, encore"
      },
  
      {
        "type": "section",
        "section": "Verse 1"
      },
      {
        "english": "Lá eile cac céanna",
        "irish": "Another day, same shit"
      },
      {
        "english": "'Dom an stuif, cuirfidh mé ceann le chéile",
        "irish": "Give me the stuff, I'll roll one"
      },
      {
        "english": "Móglaí an tógalaí fáilte chuig an bráinse is úra glas de na hóglaigh",
        "irish": "Móglaí the builder, welcome to the freshest green branch of the volunteers"
      },
      {
        "english": "Ceithre uair is fichid",
        "irish": "Twenty-four (24)"
      },
      {
        "english": "Cead rud ar maidin agus mall in san oíche",
        "irish": "One thing in the morning, and late into the night"
      },
      {
        "english": "Fuck all else le bheith déanamh thart anseo",
        "irish": "Fuck all else to be at around here"
      },
      {
        "english": "Anois ar ais chuig an siopa to get a pack of raws",
        "irish": "Now back to the shop to get some rolling papers"
      },
      {
        "english": "Caught in a loop like I'm tryna read a book but it's the same page over and over and over and over and over and over",
        "irish": "Gafa i lúb, ag léamh an leabhair céanna arís is arís eile"
      },
      {
        "english": "Caught in the loop like I'm tryna read a book but it's the same page over and over and over and over and over and over",
        "irish": "Gafa i lúb, ag léamh an leabhair chéanna arís is arís eile"
      },
      {
        "english": "Ah fuck I'll just watch a movie",
        "irish": "Ah fuck é, féachfaidh mé ar scannán"
      },
  
      {
        "type": "section",
        "section": "Bridge"
      },
      {
        "english": "Gafa sa loop, groundhog day point two",
        "irish": "Stuck in a loop, Groundhog Day 2.0"
      },
      {
        "english": "It's been too long, I need an encore and sweaty balls too",
        "irish": "Tá sé rófhada, tá encore agus liathróidí allasacha de dhíth orm"
      },
      {
        "english": "Gafa sa loop, nothin' to do",
        "irish": "Stuck in a loop, níl faic le déanamh"
      },
      {
        "english": "It's been too long, I need an encore and sweaty balls too",
        "irish": "Tá sé rófhada, tá encore agus liathróidí allasacha de dhíth orm"
      },
  
      {
        "type": "section",
        "section": "Interlude"
      },
      {
        "english": "Why? What are we gonna do tomorrow night?",
        "irish": "Cén fáth? Cad a dhéanfaidh muid oíche amárach?"
      },
      {
        "english": "The same thing we do every night, Pinky. Try to take—",
        "irish": "An rud céanna a dhéanaimid gach oíche, Pinky. Déan iarracht glacadh—"
      },
      {
        "english": "Drugs",
        "irish": "Drugaí"
      },
  
      {
        "type": "section",
        "section": "Verse 2"
      },
      {
        "english": "I miss love buzz hugs 'is ag ól mo chuid le festival thugs",
        "irish": "I miss the hugs and drinking my share with festival thugs"
      },
      {
        "english": "I mo mucked up guds, ag suppáil suds le random cunts",
        "irish": "In my wrecked guts, neckin' pints with random lads"
      },
      {
        "english": "Ach i rith an amá, dhá harp déag agus mála Maradonna",
        "irish": "But during the day, twelve Harps and a Maradona bag"
      },
      {
        "english": "And I wanna get a half or a q then I laugh at the news as the madness ensues, tá mé gafa sa loop",
        "irish": "And I want a half or a quarter, laugh at the news as madness erupts, I'm stuck in the loop"
      },
  
      {
        "type": "section",
        "section": "Bridge (reprise)"
      },
      {
        "english": "Gafa sa loop, groundhog day point two",
        "irish": "Gafa sa lúb, Groundhog Day 2.0"
      },
      {
        "english": "It's been too long, I need an encore and sweaty balls too",
        "irish": "Tá sé rófhada, tá encore agus liathróidí allasacha de dhíth orm"
      },
      {
        "english": "Gafa sa loop, nothin' to do",
        "irish": "Gafa sa lúb, níl faic le déanamh"
      },
      {
        "english": "It's been too long, I need an encore and sweaty balls too",
        "irish": "Tá sé rófhada, tá encore agus liathróidí allasacha de dhíth orm"
      },
  
      {
        "type": "section",
        "section": "Final Hook"
      },
      {
        "english": "Thart agus thart",
        "irish": "Thart agus thart"
      },
      {
        "english": "Big skins, thíos ag an mini mart",
        "irish": "Páipéir mhóra, thíos ag an mini mart"
      },
      {
        "english": "Few loose capri sun and a mars bar",
        "irish": "Cúpla Capri Sun agus barra Mars"
      },
      {
        "english": "Dúid mhór salach ansin tá mé thar barr",
        "irish": "Dúid mhór salach and now I'm grand"
      },
      {
        "english": "Thart agus thart",
        "irish": "Thart agus thart"
      },
      {
        "english": "Cosúil le mo mhéilteoir ya",
        "irish": "Like my grinder, yeah"
      },
      {
        "english": "Fear beag gnaitheach when I'm on tour",
        "irish": "Fear beag gnóthach when I'm on tour"
      },
      {
        "english": "No top, moshpit, sweaty balls, encore",
        "irish": "Gan léine, i moshpit, liathróidí allasacha, encore"
      }
    ]
  }
  